{"id": 418365, "media_id": "2316569", "title": {"english": "[Tomonaga Kenji] Mahoutsukai Oku-sama. | Magical Housewife. (COMIC HOTMiLK Koime Vol. 23) [English] [ConTL] [Digital]", "japanese": "[\u53cb\u6c38\u30b1\u30f3\u30b8] \u307e\u307b\u3046\u3064\u304b\u3044\u5965\u69d8\u3002 (\u30b3\u30df\u30c3\u30af\u30db\u30c3\u30c8\u30df\u30eb\u30af\u6fc3\u3044\u3081 vol.23) [\u82f1\u8a33] [DL\u7248]", "pretty": "Mahoutsukai Oku-sama. | Magical Housewife."}, "images": {"pages": [{"t": "j", "w": 1280, "h": 1808}, {"t": "j", "w": 1280, "h": 1808}, {"t": "j", "w": 1280, "h": 1808}, {"t": "j", "w": 1280, "h": 1808}, {"t": "j", "w": 1280, "h": 1808}, {"t": "j", "w": 1280, "h": 1808}, {"t": "j", "w": 1280, "h": 1808}, {"t": "j", "w": 1280, "h": 1808}, {"t": "j", "w": 1280, "h": 1808}, {"t": "j", "w": 1280, "h": 1808}, {"t": "j", "w": 1280, "h": 1808}, {"t": "j", "w": 1280, "h": 1808}, {"t": "j", "w": 1280, "h": 1808}, {"t": "j", "w": 1280, "h": 1808}, {"t": "j", "w": 1280, "h": 1808}, {"t": "j", "w": 1280, "h": 1808}, {"t": "j", "w": 1280, "h": 1808}, {"t": "j", "w": 1280, "h": 1808}, {"t": "j", "w": 1280, "h": 1808}, {"t": "j", "w": 1280, "h": 1808}, {"t": "j", "w": 1280, "h": 823}, {"t": "j", "w": 1280, "h": 824}], "cover": {"t": "j", "w": 350, "h": 494}, "thumbnail": {"t": "j", "w": 250, "h": 353}}, "scanlator": "", "upload_date": 1662164281, "tags": [{"id": 1207, "type": "tag", "name": "milf", "url": "/tag/milf/", "count": 32997}, {"id": 2937, "type": "tag", "name": "big breasts", "url": "/tag/big-breasts/", "count": 140852}, {"id": 6817, "type": "tag", "name": "unusual pupils", "url": "/tag/unusual-pupils/", "count": 11171}, {"id": 12227, "type": "language", "name": "english", "url": "/language/english/", "count": 98466}, {"id": 13720, "type": "tag", "name": "nakadashi", "url": "/tag/nakadashi/", "count": 64335}, {"id": 13989, "type": "tag", "name": "ahegao", "url": "/tag/ahegao/", "count": 39312}, {"id": 17249, "type": "language", "name": "translated", "url": "/language/translated/", "count": 169777}, {"id": 17531, "type": "tag", "name": "cosplaying", "url": "/tag/cosplaying/", "count": 2311}, {"id": 19289, "type": "artist", "name": "tomonaga kenji", "url": "/artist/tomonaga-kenji/", "count": 72}, {"id": 33173, "type": "category", "name": "manga", "url": "/category/manga/", "count": 103302}, {"id": 35762, "type": "tag", "name": "sole female", "url": "/tag/sole-female/", "count": 109027}, {"id": 35763, "type": "tag", "name": "sole male", "url": "/tag/sole-male/", "count": 96999}], "num_pages": 22, "num_favorites": 20330}