{"id": "425521", "media_id": "2360017", "title": {"english": "[ eichi ] ( suzuna mikan ) hitomi no iro wa yoru no naka The IDOLM@STER SideM", "japanese": "[ \u30a8\u30a4\u30c1] ( \u83d8\u307f\u304b\u3093) \u77b3\u306e\u8272\u306f\u591c\u306e\u306a\u304b  \u30a2\u30a4\u30c9\u30eb\u30de\u30b9\u30bf\u30fc \u30b5\u30a4\u30c9\u30a8\u30e0", "pretty": "hitomi no iro wa yoru no naka The IDOLM@STER SideM"}, "images": {"pages": [{"t": "j", "w": 600, "h": 600}, {"t": "j", "w": 1280, "h": 2127}, {"t": "j", "w": 1280, "h": 2006}, {"t": "j", "w": 1280, "h": 2073}, {"t": "j", "w": 1280, "h": 2092}, {"t": "j", "w": 1280, "h": 2190}, {"t": "j", "w": 1280, "h": 2130}, {"t": "j", "w": 1280, "h": 2240}, {"t": "j", "w": 1280, "h": 2050}, {"t": "j", "w": 1280, "h": 2041}, {"t": "j", "w": 1280, "h": 2039}, {"t": "j", "w": 1280, "h": 2037}, {"t": "j", "w": 1280, "h": 2048}, {"t": "j", "w": 1280, "h": 2154}, {"t": "j", "w": 1280, "h": 2117}, {"t": "j", "w": 1280, "h": 2115}, {"t": "j", "w": 1280, "h": 2243}, {"t": "j", "w": 1280, "h": 2143}, {"t": "j", "w": 1280, "h": 2071}, {"t": "j", "w": 1280, "h": 2037}, {"t": "j", "w": 1280, "h": 2061}, {"t": "j", "w": 1280, "h": 1771}, {"t": "j", "w": 1280, "h": 2041}, {"t": "j", "w": 1280, "h": 2088}, {"t": "j", "w": 1280, "h": 2083}, {"t": "j", "w": 1280, "h": 2109}, {"t": "j", "w": 1280, "h": 2058}, {"t": "j", "w": 1280, "h": 2074}, {"t": "j", "w": 1280, "h": 1775}], "cover": {"t": "j", "w": 350, "h": 350}, "thumbnail": {"t": "j", "w": 250, "h": 250}}, "scanlator": "", "upload_date": 1666743289, "tags": [{"id": 6346, "type": "language", "name": "japanese", "url": "/language/japanese/", "count": 236814}, {"id": 21712, "type": "tag", "name": "males only", "url": "/tag/males-only/", "count": 33636}, {"id": 23895, "type": "tag", "name": "yaoi", "url": "/tag/yaoi/", "count": 40542}, {"id": 33172, "type": "category", "name": "doujinshi", "url": "/category/doujinshi/", "count": 310308}, {"id": 120523, "type": "parody", "name": "the idolmaster sidem", "url": "/parody/the-idolmaster-sidem/", "count": 58}], "num_pages": 29, "num_favorites": 0}