{"id": 432454, "media_id": "2406626", "title": {"english": "[miso] Nue no Naku Yoru ni | \u4e8e\u9d7a\u557c\u4e4b\u591c Ch. 1-4 [Chinese] [\u5192\u9669\u8005\u516c\u4f1a] [Digital]", "japanese": "[miso] \u9d7a\u306e\u557c\u304f\u591c\u306b \u7b2c1-4\u8a71 [\u4e2d\u56fd\u7ffb\u8a33] [DL\u7248]", "pretty": "Nue no Naku Yoru ni | \u4e8e\u9d7a\u557c\u4e4b\u591c Ch. 1-4"}, "images": {"pages": [{"t": "j", "w": 1125, "h": 1600}, {"t": "j", "w": 1125, "h": 1600}, {"t": "j", "w": 1125, "h": 1600}, {"t": "j", "w": 1125, "h": 1600}, {"t": "j", "w": 1125, "h": 1600}, {"t": "j", "w": 1125, "h": 1600}, {"t": "j", "w": 1125, "h": 1600}, {"t": "j", "w": 1125, "h": 1600}, {"t": "j", "w": 1125, "h": 1600}, {"t": "j", "w": 1125, "h": 1600}, {"t": "j", "w": 1125, "h": 1600}, {"t": "j", "w": 1125, "h": 1600}, {"t": "j", "w": 1125, "h": 1600}, {"t": "j", "w": 1125, "h": 1600}, {"t": "j", "w": 1125, "h": 1600}, {"t": "j", "w": 1125, "h": 1600}, {"t": "j", "w": 1125, "h": 1600}, {"t": "j", "w": 1125, "h": 1600}, {"t": "j", "w": 1125, "h": 1600}, {"t": "j", "w": 1125, "h": 1600}, {"t": "j", "w": 1125, "h": 1600}, {"t": "j", "w": 1125, "h": 1600}, {"t": "j", "w": 1125, "h": 1600}, {"t": "j", "w": 1125, "h": 1600}, {"t": "j", "w": 1125, "h": 1600}, {"t": "j", "w": 1125, "h": 1600}, {"t": "j", "w": 1125, "h": 1600}, {"t": "j", "w": 1125, "h": 1600}, {"t": "j", "w": 1125, "h": 1600}, {"t": "j", "w": 1125, "h": 1600}, {"t": "j", "w": 1125, "h": 1600}, {"t": "j", "w": 1125, "h": 1600}, {"t": "j", "w": 1125, "h": 1600}, {"t": "j", "w": 1125, "h": 1600}, {"t": "j", "w": 1125, "h": 1600}, {"t": "j", "w": 1125, "h": 1600}, {"t": "j", "w": 1125, "h": 1600}, {"t": "j", "w": 1125, "h": 1600}, {"t": "j", "w": 846, "h": 1363}, {"t": "j", "w": 1125, "h": 1600}, {"t": "j", "w": 1125, "h": 1600}, {"t": "j", "w": 1125, "h": 1600}, {"t": "j", "w": 1125, "h": 1600}, {"t": "j", "w": 1125, "h": 1600}, {"t": "j", "w": 1125, "h": 1600}, {"t": "j", "w": 1125, "h": 1600}, {"t": "j", "w": 1125, "h": 1600}, {"t": "j", "w": 1125, "h": 1600}, {"t": "j", "w": 1125, "h": 1600}, {"t": "j", "w": 1125, "h": 1600}, {"t": "j", "w": 1125, "h": 1600}, {"t": "j", "w": 1125, "h": 1600}, {"t": "j", "w": 1125, "h": 1600}, {"t": "j", "w": 1125, "h": 1600}, {"t": "j", "w": 1125, "h": 1600}, {"t": "j", "w": 1125, "h": 1600}, {"t": "j", "w": 1125, "h": 1600}, {"t": "j", "w": 1125, "h": 1600}, {"t": "j", "w": 1125, "h": 1600}, {"t": "j", "w": 1125, "h": 1600}, {"t": "j", "w": 1125, "h": 1600}, {"t": "j", "w": 1125, "h": 1600}, {"t": "j", "w": 1125, "h": 1600}, {"t": "j", "w": 1125, "h": 1600}, {"t": "j", "w": 1125, "h": 1600}, {"t": "j", "w": 1125, "h": 1600}, {"t": "j", "w": 1125, "h": 1600}, {"t": "j", "w": 1125, "h": 1600}, {"t": "j", "w": 1125, "h": 1600}, {"t": "j", "w": 846, "h": 1363}, {"t": "j", "w": 1125, "h": 1600}, {"t": "j", "w": 1125, "h": 1600}, {"t": "j", "w": 1125, "h": 1600}, {"t": "j", "w": 1125, "h": 1600}, {"t": "j", "w": 1125, "h": 1600}, {"t": "j", "w": 1125, "h": 1600}, {"t": "j", "w": 1125, "h": 1600}, {"t": "j", "w": 1125, "h": 1600}, {"t": "j", "w": 1125, "h": 1600}, {"t": "j", "w": 1125, "h": 1600}, {"t": "j", "w": 1125, "h": 1600}, {"t": "j", "w": 1125, "h": 1600}, {"t": "j", "w": 1125, "h": 1600}, {"t": "j", "w": 1125, "h": 1600}, {"t": "j", "w": 1125, "h": 1600}, {"t": "j", "w": 1125, "h": 1600}, {"t": "j", "w": 1125, "h": 1600}, {"t": "j", "w": 1125, "h": 1600}, {"t": "j", "w": 1125, "h": 1600}, {"t": "j", "w": 1125, "h": 1600}, {"t": "j", "w": 1125, "h": 1600}, {"t": "j", "w": 1125, "h": 1600}, {"t": "j", "w": 1125, "h": 1600}, {"t": "j", "w": 1125, "h": 1600}, {"t": "j", "w": 1125, "h": 1600}, {"t": "j", "w": 1125, "h": 1600}, {"t": "j", "w": 1125, "h": 1600}, {"t": "j", "w": 1125, "h": 1600}, {"t": "j", "w": 1125, "h": 1600}, {"t": "j", "w": 1125, "h": 1600}, {"t": "j", "w": 1125, "h": 1600}, {"t": "j", "w": 1125, "h": 1600}, {"t": "j", "w": 846, "h": 984}, {"t": "j", "w": 1125, "h": 1600}, {"t": "j", "w": 1125, "h": 1600}, {"t": "j", "w": 1125, "h": 1600}, {"t": "j", "w": 1125, "h": 1600}, {"t": "j", "w": 1125, "h": 1600}, {"t": "j", "w": 1125, "h": 1600}, {"t": "j", "w": 1125, "h": 1600}, {"t": "j", "w": 1125, "h": 1600}, {"t": "j", "w": 1125, "h": 1600}, {"t": "j", "w": 1125, "h": 1600}, {"t": "j", "w": 1125, "h": 1600}, {"t": "j", "w": 1125, "h": 1600}, {"t": "j", "w": 1125, "h": 1600}, {"t": "j", "w": 1125, "h": 1600}, {"t": "j", "w": 1125, "h": 1600}, {"t": "j", "w": 1125, "h": 1600}, {"t": "j", "w": 1125, "h": 1600}, {"t": "j", "w": 1125, "h": 1600}, {"t": "j", "w": 1125, "h": 1600}, {"t": "j", "w": 1125, "h": 1600}, {"t": "j", "w": 1125, "h": 1600}, {"t": "j", "w": 1125, "h": 1600}, {"t": "j", "w": 1125, "h": 1600}, {"t": "j", "w": 1125, "h": 1600}, {"t": "j", "w": 1125, "h": 1600}, {"t": "j", "w": 1125, "h": 1600}, {"t": "j", "w": 1125, "h": 1600}, {"t": "j", "w": 1125, "h": 1600}, {"t": "j", "w": 1125, "h": 1600}, {"t": "j", "w": 1125, "h": 1600}, {"t": "j", "w": 846, "h": 984}], "cover": {"t": "j", "w": 350, "h": 498}, "thumbnail": {"t": "j", "w": 250, "h": 356}}, "scanlator": "", "upload_date": 1671446751, "tags": [{"id": 169, "type": "artist", "name": "miso", "url": "/artist/miso/", "count": 19}, {"id": 8378, "type": "tag", "name": "glasses", "url": "/tag/glasses/", "count": 60859}, {"id": 8739, "type": "tag", "name": "story arc", "url": "/tag/story-arc/", "count": 15258}, {"id": 17249, "type": "language", "name": "translated", "url": "/language/translated/", "count": 171148}, {"id": 21712, "type": "tag", "name": "males only", "url": "/tag/males-only/", "count": 34318}, {"id": 23895, "type": "tag", "name": "yaoi", "url": "/tag/yaoi/", "count": 41284}, {"id": 29963, "type": "language", "name": "chinese", "url": "/language/chinese/", "count": 81053}, {"id": 31044, "type": "tag", "name": "collar", "url": "/tag/collar/", "count": 20288}, {"id": 33173, "type": "category", "name": "manga", "url": "/category/manga/", "count": 103857}], "num_pages": 134, "num_favorites": 0}