{"id": 430246, "media_id": "2391924", "title": {"english": "(COMIC1 BS-sai Special) [Shouyu no Sato (Kirishima Ayu)] Ouji-sama mo Koneko-chan ni Naritai (Alice Gear Aegis) [Digital]", "japanese": "(COMIC1 BS\u796d \u30b9\u30da\u30b7\u30e3\u30eb) [\u91a4\u6cb9\u306e\u91cc (\u9727\u5cf6\u9b8e)] \u738b\u5b50\u69d8\u3082\u5b50\u732b\u3061\u3083\u3093\u306b\u306a\u308a\u305f\u3044 (\u30a2\u30ea\u30b9\u30fb\u30ae\u30a2\u30fb\u30a2\u30a4\u30ae\u30b9) [DL\u7248]", "pretty": "Oujichan ni Naritai"}, "images": {"pages": [{"t": "j", "w": 1280, "h": 1790}, {"t": "j", "w": 1280, "h": 1780}, {"t": "j", "w": 1280, "h": 1780}, {"t": "j", "w": 1280, "h": 1780}, {"t": "j", "w": 1280, "h": 1780}, {"t": "j", "w": 1280, "h": 1780}, {"t": "j", "w": 1280, "h": 1780}, {"t": "j", "w": 1280, "h": 1780}, {"t": "j", "w": 1280, "h": 1780}, {"t": "j", "w": 1280, "h": 1780}, {"t": "j", "w": 1280, "h": 1780}, {"t": "j", "w": 1280, "h": 1780}, {"t": "j", "w": 1280, "h": 1780}, {"t": "j", "w": 1280, "h": 1780}, {"t": "j", "w": 1280, "h": 1780}, {"t": "j", "w": 1280, "h": 1780}, {"t": "j", "w": 1280, "h": 1780}, {"t": "j", "w": 1280, "h": 1790}], "cover": {"t": "j", "w": 350, "h": 490}, "thumbnail": {"t": "j", "w": 250, "h": 350}}, "scanlator": "", "upload_date": 1670047149, "tags": [{"id": 6346, "type": "language", "name": "japanese", "url": "/language/japanese/", "count": 238984}, {"id": 6817, "type": "tag", "name": "unusual pupils", "url": "/tag/unusual-pupils/", "count": 11188}, {"id": 15225, "type": "tag", "name": "blowjob face", "url": "/tag/blowjob-face/", "count": 2534}, {"id": 25601, "type": "tag", "name": "small breasts", "url": "/tag/small-breasts/", "count": 9004}, {"id": 25871, "type": "tag", "name": "lingerie", "url": "/tag/lingerie/", "count": 11290}, {"id": 29366, "type": "tag", "name": "tomboy", "url": "/tag/tomboy/", "count": 4070}, {"id": 29859, "type": "tag", "name": "blowjob", "url": "/tag/blowjob/", "count": 58246}, {"id": 33172, "type": "category", "name": "doujinshi", "url": "/category/doujinshi/", "count": 314015}, {"id": 35762, "type": "tag", "name": "sole female", "url": "/tag/sole-female/", "count": 109305}, {"id": 35763, "type": "tag", "name": "sole male", "url": "/tag/sole-male/", "count": 97203}, {"id": 50486, "type": "tag", "name": "tail plug", "url": "/tag/tail-plug/", "count": 2115}, {"id": 72975, "type": "group", "name": "shouyu no sato", "url": "/group/shouyu-no-sato/", "count": 47}, {"id": 72976, "type": "artist", "name": "kirishima ayu", "url": "/artist/kirishima-ayu/", "count": 98}, {"id": 81774, "type": "tag", "name": "kemonomimi", "url": "/tag/kemonomimi/", "count": 13104}, {"id": 92453, "type": "parody", "name": "alice gear aegis", "url": "/parody/alice-gear-aegis/", "count": 114}, {"id": 97795, "type": "tag", "name": "pixie cut", "url": "/tag/pixie-cut/", "count": 1253}, {"id": 104227, "type": "tag", "name": "tail", "url": "/tag/tail/", "count": 5420}], "num_pages": 18, "num_favorites": 0}