{"id": "429088", "media_id": "2383172", "title": {"english": "[No Future (\u3059\u307f\u3059\u305a\u3001\u7aef\u97f3\u4e71\u5e0c)][\u3069\u308d\u3063\u3077\u3059! (\u5927\u4eba\u306eSEXY\u7d75\u672c)]\u5ff5\u52a8\u5c11\u5973\u7480\u74a8\u661f \uff5e\u5145\u6ee1\u8272\u60c5\u9677\u9631\u7684\u5730\u4e0b\u7814\u7a76\u6240\uff5e \u6f2b\u753b\u603b\u96c6\u7bc7[\u4e2d\u56fd\u7ffb\u8a33] [DL\u7248]", "japanese": null, "pretty": "\u5ff5\u52a8\u5c11\u5973\u7480\u74a8\u661f \uff5e\u5145\u6ee1\u8272\u60c5\u9677\u9631\u7684\u5730\u4e0b\u7814\u7a76\u6240\uff5e \u6f2b\u753b\u603b\u96c6\u7bc7"}, "images": {"pages": [{"t": "j", "w": 1280, "h": 1810}, {"t": "j", "w": 1280, "h": 1807}, {"t": "j", "w": 1280, "h": 1807}, {"t": "j", "w": 1280, "h": 1807}, {"t": "j", "w": 1280, "h": 1807}, {"t": "j", "w": 1280, "h": 1807}, {"t": "j", "w": 1280, "h": 1807}, {"t": "j", "w": 1280, "h": 1807}, {"t": "j", "w": 1280, "h": 1807}, {"t": "j", "w": 1280, "h": 1807}, {"t": "j", "w": 1280, "h": 1807}, {"t": "j", "w": 1280, "h": 1807}, {"t": "j", "w": 1280, "h": 1807}, {"t": "j", "w": 1280, "h": 1807}, {"t": "j", "w": 1280, "h": 1807}, {"t": "j", "w": 1280, "h": 1807}, {"t": "j", "w": 1280, "h": 1807}, {"t": "j", "w": 1280, "h": 1807}, {"t": "j", "w": 1280, "h": 1807}, {"t": "j", "w": 1280, "h": 1807}, {"t": "j", "w": 1280, "h": 1807}, {"t": "j", "w": 1280, "h": 1807}, {"t": "j", "w": 1280, "h": 1807}, {"t": "j", "w": 1280, "h": 1807}, {"t": "j", "w": 1280, "h": 1807}, {"t": "j", "w": 1280, "h": 1807}, {"t": "j", "w": 1280, "h": 1807}, {"t": "j", "w": 1280, "h": 1807}, {"t": "j", "w": 1280, "h": 1807}, {"t": "j", "w": 1280, "h": 1807}, {"t": "j", "w": 1280, "h": 1807}, {"t": "j", "w": 1280, "h": 1807}, {"t": "j", "w": 1280, "h": 1807}, {"t": "j", "w": 1280, "h": 1807}, {"t": "j", "w": 1280, "h": 1807}, {"t": "j", "w": 1280, "h": 1807}, {"t": "j", "w": 1280, "h": 1807}, {"t": "j", "w": 1280, "h": 1807}, {"t": "j", "w": 1280, "h": 1807}, {"t": "j", "w": 1280, "h": 1807}, {"t": "j", "w": 1280, "h": 1807}, {"t": "j", "w": 1280, "h": 1807}, {"t": "j", "w": 1280, "h": 1807}, {"t": "j", "w": 1280, "h": 1807}, {"t": "j", "w": 1280, "h": 1807}, {"t": "j", "w": 1280, "h": 1807}, {"t": "j", "w": 1280, "h": 1807}, {"t": "j", "w": 1280, "h": 1807}, {"t": "j", "w": 1280, "h": 1807}, {"t": "j", "w": 1280, "h": 1812}, {"t": "j", "w": 1280, "h": 1807}], "cover": {"t": "j", "w": 350, "h": 495}, "thumbnail": {"t": "j", "w": 250, "h": 354}}, "scanlator": "", "upload_date": 1669194300, "tags": [{"id": 17249, "type": "language", "name": "translated", "url": "/language/translated/", "count": 169562}, {"id": 20905, "type": "tag", "name": "full color", "url": "/tag/full-color/", "count": 51150}, {"id": 27473, "type": "tag", "name": "mosaic censorship", "url": "/tag/mosaic-censorship/", "count": 38149}, {"id": 29963, "type": "language", "name": "chinese", "url": "/language/chinese/", "count": 80006}, {"id": 31775, "type": "tag", "name": "tentacles", "url": "/tag/tentacles/", "count": 16781}, {"id": 33172, "type": "category", "name": "doujinshi", "url": "/category/doujinshi/", "count": 313104}, {"id": 72710, "type": "artist", "name": "purinpu", "url": "/artist/purinpu/", "count": 3}, {"id": 75965, "type": "group", "name": "drops", "url": "/group/drops/", "count": 17}, {"id": 137682, "type": "group", "name": "no future", "url": "/group/no-future/", "count": 12}], "num_pages": 51, "num_favorites": 0}