{"id": 414566, "media_id": "2296237", "title": {"english": "[Oyogi] Hinnyuu de Kahanshin Dekai Succubus ni Ouen Saretari Baka ni Sare Sarenagara Ecchi Suru Hanashi.", "japanese": "[\u304a\u3088\u304e]  \u8ca7\u4e73\u3067\u4e0b\u534a\u8eab\u3067\u304b\u3044\u30b5\u30ad\u30e5\u30d0\u30b9\u306b\u5fdc\u63f4\u3055\u308c\u305f\u308a\u99ac\u9e7f\u306b\u3055\u308c\u306a\u304c\u3089\u3048\u3063\u3061\u3059\u308b\u8a71\u3002", "pretty": "Hinnyuu de Kahanshin Dekai Succubus ni Ouen Saretari Baka ni Sare Sarenagara Ecchi Suru Hanashi."}, "images": {"pages": [{"t": "j", "w": 1120, "h": 840}, {"t": "j", "w": 1000, "h": 1400}, {"t": "j", "w": 1000, "h": 1400}, {"t": "j", "w": 1000, "h": 1400}, {"t": "j", "w": 1000, "h": 1400}, {"t": "j", "w": 1000, "h": 1400}, {"t": "j", "w": 1000, "h": 1400}, {"t": "j", "w": 1000, "h": 1400}, {"t": "j", "w": 1000, "h": 1400}, {"t": "j", "w": 1000, "h": 1400}, {"t": "j", "w": 1000, "h": 1400}, {"t": "j", "w": 1000, "h": 1400}, {"t": "j", "w": 1000, "h": 1400}, {"t": "j", "w": 1000, "h": 1400}, {"t": "j", "w": 1000, "h": 1400}, {"t": "j", "w": 1000, "h": 1400}, {"t": "j", "w": 1000, "h": 1400}, {"t": "j", "w": 1000, "h": 1400}, {"t": "j", "w": 1000, "h": 1400}], "cover": {"t": "j", "w": 350, "h": 262}, "thumbnail": {"t": "j", "w": 250, "h": 188}}, "scanlator": "", "upload_date": 1660222761, "tags": [{"id": 6346, "type": "language", "name": "japanese", "url": "/language/japanese/", "count": 235736}, {"id": 16228, "type": "tag", "name": "demon girl", "url": "/tag/demon-girl/", "count": 7919}, {"id": 25601, "type": "tag", "name": "small breasts", "url": "/tag/small-breasts/", "count": 8895}, {"id": 25744, "type": "tag", "name": "cheerleader", "url": "/tag/cheerleader/", "count": 1527}, {"id": 33172, "type": "category", "name": "doujinshi", "url": "/category/doujinshi/", "count": 308549}, {"id": 35762, "type": "tag", "name": "sole female", "url": "/tag/sole-female/", "count": 106579}, {"id": 35763, "type": "tag", "name": "sole male", "url": "/tag/sole-male/", "count": 95016}, {"id": 88846, "type": "tag", "name": "horns", "url": "/tag/horns/", "count": 5365}, {"id": 90671, "type": "parody", "name": "original", "url": "/parody/original/", "count": 53375}, {"id": 104227, "type": "tag", "name": "tail", "url": "/tag/tail/", "count": 5187}], "num_pages": 19, "num_favorites": 848}