{"id": 413341, "media_id": "2287763", "title": {"english": "[R Koubou (Aru-shi)] Jikka ni Kaettara Seichoshita Jumai to Icha Love shita Ohanashi", "japanese": "[\u3042\uff5e\u308b\u5de5\u623f (\u3042\uff5e\u308b\u6c0f)] \u5b9f\u5bb6\u306b\u5e30\u3063\u305f\u3089\u6210\u9577\u3057\u305f\u5f93\u59b9\u3068\u3044\u3061\u3083\u30e9\u30d6\u3057\u305f\u304a\u8a71", "pretty": "Jikka ni Kaettara Seichoshita Jumai to Icha Love shita Ohanashi"}, "images": {"pages": [{"t": "j", "w": 1280, "h": 1781}, {"t": "j", "w": 1280, "h": 1781}, {"t": "j", "w": 1280, "h": 1781}, {"t": "j", "w": 1280, "h": 1781}, {"t": "j", "w": 1280, "h": 1781}, {"t": "j", "w": 1280, "h": 1781}, {"t": "j", "w": 1280, "h": 1781}, {"t": "j", "w": 1280, "h": 1781}, {"t": "j", "w": 1280, "h": 1781}, {"t": "j", "w": 1280, "h": 1781}, {"t": "j", "w": 1280, "h": 1781}, {"t": "j", "w": 1280, "h": 1781}, {"t": "j", "w": 1280, "h": 1781}, {"t": "j", "w": 1280, "h": 1781}, {"t": "j", "w": 1280, "h": 1781}, {"t": "j", "w": 1280, "h": 1781}, {"t": "j", "w": 1280, "h": 1781}, {"t": "j", "w": 1280, "h": 1781}, {"t": "j", "w": 1280, "h": 1781}, {"t": "j", "w": 1280, "h": 1781}, {"t": "j", "w": 1280, "h": 1781}, {"t": "j", "w": 1280, "h": 1781}, {"t": "j", "w": 1280, "h": 1781}, {"t": "j", "w": 1280, "h": 1781}, {"t": "j", "w": 1280, "h": 1781}, {"t": "j", "w": 1280, "h": 1781}], "cover": {"t": "j", "w": 350, "h": 487}, "thumbnail": {"t": "j", "w": 250, "h": 348}}, "scanlator": "", "upload_date": 1659384277, "tags": [{"id": 2937, "type": "tag", "name": "big breasts", "url": "/tag/big-breasts/", "count": 139288}, {"id": 6346, "type": "language", "name": "japanese", "url": "/language/japanese/", "count": 236517}, {"id": 19390, "type": "tag", "name": "cousin", "url": "/tag/cousin/", "count": 1921}, {"id": 20035, "type": "tag", "name": "x-ray", "url": "/tag/x-ray/", "count": 28704}, {"id": 22942, "type": "tag", "name": "incest", "url": "/tag/incest/", "count": 36817}, {"id": 30555, "type": "tag", "name": "big penis", "url": "/tag/big-penis/", "count": 15666}, {"id": 33172, "type": "category", "name": "doujinshi", "url": "/category/doujinshi/", "count": 309845}, {"id": 35762, "type": "tag", "name": "sole female", "url": "/tag/sole-female/", "count": 107208}, {"id": 35763, "type": "tag", "name": "sole male", "url": "/tag/sole-male/", "count": 95566}, {"id": 90671, "type": "parody", "name": "original", "url": "/parody/original/", "count": 53879}, {"id": 142421, "type": "group", "name": "r koubou", "url": "/group/r-koubou/", "count": 4}], "num_pages": 26, "num_favorites": 1481}