{"id": 432241, "media_id": "2405211", "title": {"english": "[Follet] Shikiyoku Paranoia Ch. 3 (COMIC Reboot Vol. 06) [Chinese] [Digital]", "japanese": "[\u3075\u3049\u308c\u3063\u3068] \u8272\u6b32\u30d1\u30e9\u30ce\u30e9\u30a4\u30a2 \u7b2c\u4e09\u8a71 (\u30b3\u30df\u30c3\u30af\u30ea\u30d6\u30fc\u30c8 Vol.06) [\u4e2d\u56fd\u7ffb\u8a33] [DL\u7248]", "pretty": "Shikiyoku Paranoia Ch. 3"}, "images": {"pages": [{"t": "j", "w": 1063, "h": 1500}, {"t": "j", "w": 1063, "h": 1500}, {"t": "j", "w": 1063, "h": 1500}, {"t": "j", "w": 1063, "h": 1500}, {"t": "j", "w": 1063, "h": 1500}, {"t": "j", "w": 1063, "h": 1500}, {"t": "j", "w": 1063, "h": 1500}, {"t": "j", "w": 1063, "h": 1500}, {"t": "j", "w": 1063, "h": 1500}, {"t": "j", "w": 1063, "h": 1500}, {"t": "j", "w": 1063, "h": 1500}, {"t": "j", "w": 1063, "h": 1500}, {"t": "j", "w": 1063, "h": 1500}, {"t": "j", "w": 1063, "h": 1500}, {"t": "j", "w": 1063, "h": 1500}, {"t": "j", "w": 1063, "h": 1500}, {"t": "j", "w": 1063, "h": 1500}, {"t": "j", "w": 1063, "h": 1500}, {"t": "j", "w": 1063, "h": 1500}, {"t": "j", "w": 1063, "h": 1500}, {"t": "g", "w": 1000, "h": 1500}, {"t": "j", "w": 1000, "h": 1500}, {"t": "j", "w": 1200, "h": 1800}, {"t": "p", "w": 1082, "h": 1500}, {"t": "j", "w": 1280, "h": 1781}, {"t": "j", "w": 1057, "h": 1500}], "cover": {"t": "j", "w": 350, "h": 494}, "thumbnail": {"t": "j", "w": 250, "h": 353}}, "scanlator": "", "upload_date": 1671320781, "tags": [{"id": 17249, "type": "language", "name": "translated", "url": "/language/translated/", "count": 171021}, {"id": 29963, "type": "language", "name": "chinese", "url": "/language/chinese/", "count": 80981}, {"id": 33173, "type": "category", "name": "manga", "url": "/category/manga/", "count": 103799}, {"id": 74201, "type": "artist", "name": "follet", "url": "/artist/follet/", "count": 31}], "num_pages": 26, "num_favorites": 0}