{"id": 426633, "media_id": "2367045", "title": {"english": "[Fukuyama Naoto] Saimin Tengoku", "japanese": "[\u5fa9\u516b\u78e8\u76f4\u514e] \u50ac\u7720\u5929\u56fd Challenge", "pretty": "Saimin Tengoku"}, "images": {"pages": [{"t": "j", "w": 1024, "h": 1024}, {"t": "j", "w": 1280, "h": 1838}, {"t": "j", "w": 1280, "h": 1838}, {"t": "j", "w": 1280, "h": 1838}, {"t": "j", "w": 1280, "h": 1838}, {"t": "j", "w": 1280, "h": 1838}, {"t": "j", "w": 1280, "h": 1838}, {"t": "j", "w": 1280, "h": 1838}, {"t": "j", "w": 1280, "h": 1838}, {"t": "j", "w": 1280, "h": 1838}, {"t": "j", "w": 1280, "h": 1838}, {"t": "j", "w": 1280, "h": 1838}, {"t": "j", "w": 1280, "h": 1838}, {"t": "j", "w": 1280, "h": 1838}, {"t": "j", "w": 1280, "h": 1838}, {"t": "j", "w": 1280, "h": 1838}, {"t": "j", "w": 1280, "h": 1838}, {"t": "j", "w": 1280, "h": 1838}, {"t": "j", "w": 1280, "h": 1838}, {"t": "j", "w": 1280, "h": 1838}, {"t": "j", "w": 1280, "h": 1838}, {"t": "j", "w": 1280, "h": 1838}, {"t": "j", "w": 1280, "h": 1838}, {"t": "j", "w": 1280, "h": 1838}, {"t": "j", "w": 1280, "h": 1838}, {"t": "j", "w": 1280, "h": 1838}, {"t": "j", "w": 1280, "h": 1838}, {"t": "j", "w": 1280, "h": 1838}, {"t": "j", "w": 1280, "h": 1838}, {"t": "j", "w": 1280, "h": 1838}, {"t": "j", "w": 1280, "h": 1838}, {"t": "j", "w": 1280, "h": 1838}, {"t": "j", "w": 1280, "h": 1838}, {"t": "j", "w": 1280, "h": 1838}, {"t": "j", "w": 1280, "h": 1838}, {"t": "j", "w": 1280, "h": 1838}, {"t": "j", "w": 1280, "h": 1838}, {"t": "j", "w": 1280, "h": 1838}, {"t": "j", "w": 1280, "h": 1838}, {"t": "j", "w": 1280, "h": 1838}, {"t": "j", "w": 1280, "h": 1838}, {"t": "j", "w": 1280, "h": 1838}, {"t": "j", "w": 1280, "h": 1838}, {"t": "j", "w": 1280, "h": 1838}, {"t": "j", "w": 1280, "h": 1838}, {"t": "j", "w": 1280, "h": 1838}, {"t": "j", "w": 1280, "h": 1838}, {"t": "j", "w": 1280, "h": 1838}, {"t": "j", "w": 1280, "h": 1838}, {"t": "j", "w": 1280, "h": 1838}, {"t": "j", "w": 1280, "h": 1838}, {"t": "j", "w": 1280, "h": 1838}, {"t": "j", "w": 1280, "h": 1838}, {"t": "j", "w": 1280, "h": 1838}, {"t": "j", "w": 1280, "h": 1838}, {"t": "j", "w": 1280, "h": 1838}, {"t": "j", "w": 1280, "h": 1838}, {"t": "j", "w": 1280, "h": 1838}, {"t": "j", "w": 1280, "h": 1838}, {"t": "j", "w": 1280, "h": 1838}, {"t": "j", "w": 1280, "h": 1838}, {"t": "j", "w": 1280, "h": 1838}, {"t": "j", "w": 1280, "h": 1838}, {"t": "j", "w": 1280, "h": 1838}, {"t": "j", "w": 1280, "h": 1838}, {"t": "j", "w": 1280, "h": 1838}, {"t": "j", "w": 1280, "h": 1838}, {"t": "j", "w": 1280, "h": 1838}, {"t": "j", "w": 1280, "h": 1838}, {"t": "j", "w": 1280, "h": 1838}, {"t": "j", "w": 1280, "h": 1838}, {"t": "j", "w": 1280, "h": 1838}, {"t": "j", "w": 1280, "h": 1838}, {"t": "j", "w": 1280, "h": 1838}, {"t": "j", "w": 1280, "h": 1838}, {"t": "j", "w": 1280, "h": 1838}, {"t": "j", "w": 1280, "h": 1838}, {"t": "j", "w": 1280, "h": 1838}, {"t": "j", "w": 1280, "h": 1838}, {"t": "j", "w": 1280, "h": 1838}, {"t": "j", "w": 1280, "h": 1838}, {"t": "j", "w": 1280, "h": 1838}, {"t": "j", "w": 1280, "h": 1838}, {"t": "j", "w": 1280, "h": 1838}, {"t": "j", "w": 1280, "h": 1838}, {"t": "j", "w": 1280, "h": 1838}, {"t": "j", "w": 1280, "h": 1838}, {"t": "j", "w": 1280, "h": 1838}, {"t": "j", "w": 1280, "h": 1838}, {"t": "j", "w": 1280, "h": 1838}, {"t": "j", "w": 1280, "h": 1838}, {"t": "j", "w": 1280, "h": 1838}, {"t": "j", "w": 1280, "h": 1838}, {"t": "j", "w": 1280, "h": 1838}, {"t": "j", "w": 1280, "h": 1838}, {"t": "j", "w": 1280, "h": 1838}, {"t": "j", "w": 1280, "h": 1838}, {"t": "j", "w": 1280, "h": 1838}, {"t": "j", "w": 1280, "h": 1838}, {"t": "j", "w": 1280, "h": 1838}, {"t": "j", "w": 1280, "h": 1838}, {"t": "j", "w": 1280, "h": 1838}, {"t": "j", "w": 1280, "h": 1838}, {"t": "j", "w": 1280, "h": 1838}, {"t": "j", "w": 1280, "h": 1838}, {"t": "j", "w": 1280, "h": 1838}, {"t": "j", "w": 1280, "h": 1838}, {"t": "j", "w": 1280, "h": 1838}, {"t": "j", "w": 1280, "h": 1838}, {"t": "j", "w": 1280, "h": 1838}, {"t": "j", "w": 1280, "h": 1838}, {"t": "j", "w": 1280, "h": 1838}, {"t": "j", "w": 1280, "h": 1838}, {"t": "j", "w": 1280, "h": 1838}, {"t": "j", "w": 1280, "h": 1838}, {"t": "j", "w": 1280, "h": 1838}, {"t": "j", "w": 1280, "h": 1838}, {"t": "j", "w": 1280, "h": 1838}, {"t": "j", "w": 1280, "h": 1838}, {"t": "j", "w": 1280, "h": 1838}, {"t": "j", "w": 1280, "h": 1838}, {"t": "j", "w": 1280, "h": 1838}, {"t": "j", "w": 1280, "h": 1838}, {"t": "j", "w": 1280, "h": 1838}, {"t": "j", "w": 1280, "h": 1838}, {"t": "j", "w": 1280, "h": 1838}, {"t": "j", "w": 1280, "h": 1838}, {"t": "j", "w": 1280, "h": 1838}, {"t": "j", "w": 1280, "h": 1838}, {"t": "j", "w": 1280, "h": 1838}, {"t": "j", "w": 1280, "h": 1838}, {"t": "j", "w": 1280, "h": 1838}, {"t": "j", "w": 1280, "h": 1838}, {"t": "j", "w": 1280, "h": 1838}, {"t": "j", "w": 1280, "h": 1838}, {"t": "j", "w": 1280, "h": 1838}, {"t": "j", "w": 1280, "h": 1838}, {"t": "j", "w": 1280, "h": 1838}, {"t": "j", "w": 1280, "h": 1838}, {"t": "j", "w": 1280, "h": 1838}, {"t": "j", "w": 1280, "h": 1838}], "cover": {"t": "j", "w": 350, "h": 350}, "thumbnail": {"t": "j", "w": 250, "h": 250}}, "scanlator": "", "upload_date": 1667442221, "tags": [{"id": 2937, "type": "tag", "name": "big breasts", "url": "/tag/big-breasts/", "count": 139889}, {"id": 8653, "type": "tag", "name": "netorare", "url": "/tag/netorare/", "count": 24247}, {"id": 12227, "type": "language", "name": "english", "url": "/language/english/", "count": 97833}, {"id": 13989, "type": "tag", "name": "ahegao", "url": "/tag/ahegao/", "count": 39080}, {"id": 17249, "type": "language", "name": "translated", "url": "/language/translated/", "count": 168338}, {"id": 20617, "type": "tag", "name": "mind control", "url": "/tag/mind-control/", "count": 14058}, {"id": 20738, "type": "artist", "name": "fukuyama naoto", "url": "/artist/fukuyama-naoto/", "count": 296}, {"id": 30555, "type": "tag", "name": "big penis", "url": "/tag/big-penis/", "count": 15758}, {"id": 33173, "type": "category", "name": "manga", "url": "/category/manga/", "count": 102711}], "num_pages": 141, "num_favorites": 0}