{"id": 417936, "media_id": "2314107", "title": {"english": "(C100) [Nerimono Koujou (Various)] Osaki Amana Dosukebe Goudoushi Amanashicomeria (THE iDOLM@STER: Shiny Colors) [Chinese] [\u7981\u6f2b\u6f22\u5316\u7d44]", "japanese": "(C100) [\u7df4\u308a\u7269\u5de5\u5834 (\u3088\u308d\u305a)] \u5927\u5d0e\u7518\u5948\u30c9\u30b9\u30b1\u30d9\u5408\u540c\u8a8c\u300e\u30a2\u30de\u30ca\u30b7\u30b3\u30e1\u30ea\u30a2\u300f (\u30a2\u30a4\u30c9\u30eb\u30de\u30b9\u30bf\u30fc \u30b7\u30e3\u30a4\u30cb\u30fc\u30ab\u30e9\u30fc\u30ba) [\u4e2d\u56fd\u7ffb\u8a33]", "pretty": "Osaki Amana Dosukebe Goudoushi Amanashicomeria"}, "images": {"pages": [{"t": "j", "w": 1280, "h": 1836}, {"t": "j", "w": 1280, "h": 1861}, {"t": "j", "w": 1280, "h": 1861}, {"t": "j", "w": 1280, "h": 1831}, {"t": "j", "w": 1280, "h": 1838}, {"t": "j", "w": 1280, "h": 1845}, {"t": "j", "w": 1280, "h": 1840}, {"t": "j", "w": 1280, "h": 1835}, {"t": "j", "w": 1280, "h": 1840}, {"t": "j", "w": 1280, "h": 1839}, {"t": "j", "w": 1280, "h": 1839}, {"t": "j", "w": 1280, "h": 1838}, {"t": "j", "w": 1280, "h": 1836}, {"t": "j", "w": 1280, "h": 1846}, {"t": "j", "w": 1280, "h": 1835}, {"t": "j", "w": 1280, "h": 1843}, {"t": "j", "w": 1280, "h": 1836}, {"t": "j", "w": 1280, "h": 1837}, {"t": "j", "w": 1280, "h": 1839}, {"t": "j", "w": 1280, "h": 1836}, {"t": "j", "w": 1280, "h": 1838}, {"t": "j", "w": 1280, "h": 1838}, {"t": "j", "w": 1280, "h": 1842}, {"t": "j", "w": 1280, "h": 1839}, {"t": "j", "w": 1280, "h": 1844}, {"t": "j", "w": 1280, "h": 1839}, {"t": "j", "w": 1280, "h": 1837}, {"t": "j", "w": 1280, "h": 1837}, {"t": "j", "w": 1280, "h": 1846}, {"t": "j", "w": 1280, "h": 1841}, {"t": "j", "w": 1280, "h": 1833}, {"t": "j", "w": 1280, "h": 1843}, {"t": "j", "w": 1280, "h": 1842}, {"t": "j", "w": 1280, "h": 1847}, {"t": "j", "w": 1280, "h": 1849}, {"t": "j", "w": 1280, "h": 1848}, {"t": "j", "w": 1280, "h": 1848}, {"t": "j", "w": 1280, "h": 1836}, {"t": "j", "w": 1280, "h": 1841}, {"t": "j", "w": 1280, "h": 1843}, {"t": "j", "w": 1280, "h": 1847}, {"t": "j", "w": 1280, "h": 1848}, {"t": "j", "w": 1280, "h": 1845}, {"t": "j", "w": 1280, "h": 1850}, {"t": "j", "w": 1280, "h": 1845}, {"t": "j", "w": 1280, "h": 1847}, {"t": "j", "w": 1280, "h": 1846}, {"t": "j", "w": 1280, "h": 1845}, {"t": "j", "w": 1280, "h": 1846}, {"t": "j", "w": 1280, "h": 1849}, {"t": "j", "w": 1280, "h": 1844}, {"t": "j", "w": 1280, "h": 1847}, {"t": "j", "w": 1280, "h": 1848}, {"t": "j", "w": 1280, "h": 1842}, {"t": "j", "w": 1280, "h": 1846}, {"t": "j", "w": 1280, "h": 1842}, {"t": "j", "w": 1280, "h": 1842}, {"t": "j", "w": 1280, "h": 1843}, {"t": "j", "w": 1280, "h": 1841}, {"t": "j", "w": 1280, "h": 1842}, {"t": "j", "w": 1280, "h": 1845}, {"t": "j", "w": 1280, "h": 1841}, {"t": "j", "w": 1280, "h": 1845}, {"t": "j", "w": 1280, "h": 1842}, {"t": "j", "w": 1280, "h": 1845}, {"t": "j", "w": 1280, "h": 1844}, {"t": "j", "w": 1280, "h": 1842}, {"t": "j", "w": 1280, "h": 1849}, {"t": "j", "w": 1280, "h": 1854}, {"t": "j", "w": 1280, "h": 1853}, {"t": "j", "w": 1280, "h": 1854}, {"t": "j", "w": 1280, "h": 1848}, {"t": "j", "w": 1280, "h": 1847}, {"t": "j", "w": 1280, "h": 1844}, {"t": "j", "w": 1280, "h": 1845}, {"t": "j", "w": 1280, "h": 1850}, {"t": "j", "w": 1280, "h": 1847}, {"t": "j", "w": 1280, "h": 1845}, {"t": "j", "w": 1280, "h": 1847}, {"t": "j", "w": 1280, "h": 1847}, {"t": "j", "w": 1280, "h": 1847}, {"t": "j", "w": 1280, "h": 1850}, {"t": "j", "w": 1280, "h": 1849}, {"t": "j", "w": 1280, "h": 1843}, {"t": "j", "w": 1280, "h": 1845}, {"t": "j", "w": 1280, "h": 1843}, {"t": "j", "w": 1280, "h": 1850}, {"t": "j", "w": 1280, "h": 1845}, {"t": "j", "w": 1280, "h": 1845}, {"t": "j", "w": 1280, "h": 1843}, {"t": "j", "w": 1280, "h": 1844}, {"t": "j", "w": 1280, "h": 1849}, {"t": "j", "w": 1280, "h": 1849}, {"t": "j", "w": 1280, "h": 1855}, {"t": "j", "w": 1280, "h": 1858}, {"t": "j", "w": 1280, "h": 1851}, {"t": "j", "w": 1280, "h": 1858}, {"t": "j", "w": 1280, "h": 1855}, {"t": "j", "w": 1280, "h": 1856}, {"t": "j", "w": 1280, "h": 1858}, {"t": "j", "w": 1280, "h": 1858}, {"t": "j", "w": 1280, "h": 1854}, {"t": "j", "w": 1280, "h": 1852}, {"t": "j", "w": 1280, "h": 1850}, {"t": "j", "w": 1280, "h": 1856}, {"t": "j", "w": 1280, "h": 1848}, {"t": "j", "w": 1280, "h": 1848}, {"t": "j", "w": 1280, "h": 1849}, {"t": "j", "w": 1280, "h": 1850}, {"t": "j", "w": 1280, "h": 1852}, {"t": "j", "w": 1280, "h": 1856}, {"t": "j", "w": 1280, "h": 1849}, {"t": "j", "w": 1280, "h": 1852}, {"t": "j", "w": 1280, "h": 1846}, {"t": "j", "w": 1280, "h": 923}, {"t": "j", "w": 1280, "h": 1848}, {"t": "j", "w": 1280, "h": 1854}, {"t": "j", "w": 1280, "h": 1853}, {"t": "j", "w": 1280, "h": 1851}, {"t": "j", "w": 1280, "h": 1856}, {"t": "j", "w": 1280, "h": 1849}, {"t": "j", "w": 1280, "h": 1850}, {"t": "j", "w": 1280, "h": 1849}, {"t": "j", "w": 1280, "h": 1851}, {"t": "j", "w": 1280, "h": 1847}, {"t": "j", "w": 1280, "h": 1853}, {"t": "j", "w": 1280, "h": 1855}, {"t": "j", "w": 1280, "h": 1800}], "cover": {"t": "j", "w": 350, "h": 502}, "thumbnail": {"t": "j", "w": 250, "h": 358}}, "scanlator": "", "upload_date": 1661941334, "tags": [{"id": 17249, "type": "language", "name": "translated", "url": "/language/translated/", "count": 163778}, {"id": 20925, "type": "parody", "name": "the idolmaster", "url": "/parody/the-idolmaster/", "count": 11627}, {"id": 29963, "type": "language", "name": "chinese", "url": "/language/chinese/", "count": 76249}, {"id": 33172, "type": "category", "name": "doujinshi", "url": "/category/doujinshi/", "count": 304528}, {"id": 99201, "type": "character", "name": "amana osaki", "url": "/character/amana-osaki/", "count": 64}, {"id": 108118, "type": "tag", "name": "goudoushi", "url": "/tag/goudoushi/", "count": 427}], "num_pages": 128, "num_favorites": 0}