{"id": 413162, "media_id": "2286467", "title": {"english": "[Wakabatei] SEX Haitatsu Appli De\u25cfkan de Kurokami Bob JK o Ie ni Yonde Genkan Kosoku Nuki Fella Tachi Back Demae SEX de Nuite morau Hon", "japanese": "[\u308f\u304b\u3070\u5e1d]  SEX\u914d\u9054\u30a2\u30d7\u30ea\u51fa\u25cf\u59e6\u3067\u9ed2\u9aea\u30dc\u30d6JK\u3092\u5bb6\u306b\u547c\u3093\u3067\u7384\u95a2\u9ad8\u901f\u629c\u304d\u30d5\u30a7\u30e9\u7acb\u3061\u30d0\u30c3\u30af\u51fa\u524dSEX\u3067\u629c\u3044\u3066\u3082\u3089\u3046\u672c", "pretty": "SEX Haitatsu Appli De\u25cfkan de Kurokami Bob JK o Ie ni Yonde Genkan Kosoku Nuki Fella Tachi Back Demae SEX de Nuite morau Hon"}, "images": {"pages": [{"t": "j", "w": 1100, "h": 1556}, {"t": "j", "w": 1100, "h": 1556}, {"t": "j", "w": 1100, "h": 1558}, {"t": "j", "w": 1100, "h": 1558}, {"t": "j", "w": 1100, "h": 1558}, {"t": "j", "w": 1100, "h": 1558}, {"t": "j", "w": 1100, "h": 1558}, {"t": "j", "w": 1100, "h": 1558}, {"t": "j", "w": 1100, "h": 1558}, {"t": "j", "w": 1100, "h": 1558}, {"t": "j", "w": 1100, "h": 1558}, {"t": "j", "w": 1100, "h": 1558}, {"t": "j", "w": 1100, "h": 1558}, {"t": "j", "w": 1100, "h": 1558}, {"t": "j", "w": 1100, "h": 1558}, {"t": "j", "w": 1100, "h": 1558}, {"t": "j", "w": 1100, "h": 1558}, {"t": "j", "w": 1100, "h": 1558}, {"t": "j", "w": 1100, "h": 1558}, {"t": "j", "w": 1100, "h": 1558}, {"t": "j", "w": 1100, "h": 1558}, {"t": "j", "w": 1100, "h": 1558}, {"t": "j", "w": 1100, "h": 1558}, {"t": "j", "w": 1100, "h": 1558}, {"t": "j", "w": 1100, "h": 1558}, {"t": "j", "w": 1100, "h": 1558}, {"t": "j", "w": 1100, "h": 1558}, {"t": "j", "w": 1100, "h": 1558}, {"t": "j", "w": 1100, "h": 1558}, {"t": "j", "w": 1100, "h": 1558}, {"t": "j", "w": 1100, "h": 1558}, {"t": "j", "w": 1100, "h": 1556}], "cover": {"t": "j", "w": 350, "h": 495}, "thumbnail": {"t": "j", "w": 250, "h": 354}}, "scanlator": "", "upload_date": 1659263253, "tags": [{"id": 6346, "type": "language", "name": "japanese", "url": "/language/japanese/", "count": 232689}, {"id": 10314, "type": "tag", "name": "schoolgirl uniform", "url": "/tag/schoolgirl-uniform/", "count": 67970}, {"id": 12695, "type": "tag", "name": "prostitution", "url": "/tag/prostitution/", "count": 8005}, {"id": 12824, "type": "tag", "name": "condom", "url": "/tag/condom/", "count": 8815}, {"id": 29859, "type": "tag", "name": "blowjob", "url": "/tag/blowjob/", "count": 55737}, {"id": 33172, "type": "category", "name": "doujinshi", "url": "/category/doujinshi/", "count": 302852}, {"id": 90671, "type": "parody", "name": "original", "url": "/parody/original/", "count": 51254}], "num_pages": 32, "num_favorites": 1438}