{"id": 412963, "media_id": "2285436", "title": {"english": "[H.B.A (Usagi Nagomu)] Yuukyuu no Shou Elf 4 \"Mugen\" Chuhen [Chinese]  [Digital]", "japanese": "[H.B.A (\u3046\u3055\u304e\u306a\u3054\u3080)] \u60a0\u4e45\u306e\u5a3c\u30a8\u30eb\u30d54\u300c\u5922\u5e7b\u300d\u4e2d\u7de8 [\u4e2d\u56fd\u7ffb\u8a33] [DL\u7248]", "pretty": "Yuukyuu no Shou Elf 4 \"Mugen\" Chuhen"}, "images": {"pages": [{"t": "j", "w": 1280, "h": 1808}, {"t": "j", "w": 1280, "h": 1808}, {"t": "j", "w": 1280, "h": 1808}, {"t": "j", "w": 1280, "h": 1808}, {"t": "j", "w": 1280, "h": 1808}, {"t": "j", "w": 1280, "h": 1808}, {"t": "j", "w": 1280, "h": 1808}, {"t": "j", "w": 1280, "h": 1808}, {"t": "j", "w": 1280, "h": 1808}, {"t": "j", "w": 1280, "h": 1808}, {"t": "j", "w": 1280, "h": 1808}, {"t": "j", "w": 1280, "h": 1808}, {"t": "j", "w": 1280, "h": 1808}, {"t": "j", "w": 1280, "h": 1808}, {"t": "j", "w": 1280, "h": 1808}, {"t": "j", "w": 1280, "h": 1808}, {"t": "j", "w": 1280, "h": 1808}, {"t": "j", "w": 1280, "h": 1808}, {"t": "j", "w": 1280, "h": 1808}, {"t": "j", "w": 1280, "h": 1808}, {"t": "j", "w": 1280, "h": 1808}, {"t": "j", "w": 1280, "h": 1808}, {"t": "j", "w": 1280, "h": 1808}, {"t": "j", "w": 1280, "h": 1808}, {"t": "j", "w": 1280, "h": 1808}, {"t": "j", "w": 1280, "h": 1808}, {"t": "j", "w": 1280, "h": 1808}, {"t": "j", "w": 1280, "h": 1808}, {"t": "j", "w": 1280, "h": 1808}, {"t": "j", "w": 1280, "h": 1808}, {"t": "j", "w": 1280, "h": 1808}, {"t": "j", "w": 1280, "h": 1808}, {"t": "j", "w": 1280, "h": 1808}, {"t": "j", "w": 1280, "h": 1808}, {"t": "j", "w": 1280, "h": 1808}, {"t": "j", "w": 1280, "h": 1808}], "cover": {"t": "j", "w": 350, "h": 494}, "thumbnail": {"t": "j", "w": 250, "h": 353}}, "scanlator": "", "upload_date": 1659183991, "tags": [{"id": 832, "type": "tag", "name": "elf", "url": "/tag/elf/", "count": 7179}, {"id": 2937, "type": "tag", "name": "big breasts", "url": "/tag/big-breasts/", "count": 135392}, {"id": 5556, "type": "artist", "name": "usagi nagomu", "url": "/artist/usagi-nagomu/", "count": 96}, {"id": 17249, "type": "language", "name": "translated", "url": "/language/translated/", "count": 161320}, {"id": 21572, "type": "tag", "name": "multi-work series", "url": "/tag/multi-work-series/", "count": 24945}, {"id": 25614, "type": "tag", "name": "paizuri", "url": "/tag/paizuri/", "count": 28729}, {"id": 29963, "type": "language", "name": "chinese", "url": "/language/chinese/", "count": 74651}, {"id": 33172, "type": "category", "name": "doujinshi", "url": "/category/doujinshi/", "count": 300424}, {"id": 51167, "type": "group", "name": "heavy bunny addiction | h.b.a", "url": "/group/heavy-bunny-addiction-h-b-a/", "count": 1}, {"id": 85295, "type": "tag", "name": "twintails", "url": "/tag/twintails/", "count": 17548}], "num_pages": 36, "num_favorites": 0}