{"id": 429512, "media_id": "2386377", "title": {"english": "[\u307d\u308a\u3046\u308c\u305f\u3093] \u3068\u3042\u308bP\u6d3b\u5973\u5b50", "japanese": "[\u307d\u308a\u3046\u308c\u305f\u3093] \u3068\u3042\u308bP\u6d3b\u5973\u5b50", "pretty": "\u3068\u3042\u308bP\u6d3b\u5973\u5b50"}, "images": {"pages": [{"t": "j", "w": 1200, "h": 630}, {"t": "j", "w": 1280, "h": 1807}, {"t": "j", "w": 1280, "h": 1807}, {"t": "j", "w": 1280, "h": 1807}, {"t": "j", "w": 1280, "h": 907}, {"t": "j", "w": 1280, "h": 907}, {"t": "j", "w": 1280, "h": 907}, {"t": "j", "w": 1280, "h": 907}, {"t": "j", "w": 1280, "h": 907}], "cover": {"t": "j", "w": 350, "h": 184}, "thumbnail": {"t": "j", "w": 250, "h": 131}}, "scanlator": "", "upload_date": 1669512801, "tags": [{"id": 4435, "type": "tag", "name": "gag", "url": "/tag/gag/", "count": 8946}, {"id": 6346, "type": "language", "name": "japanese", "url": "/language/japanese/", "count": 238627}, {"id": 6817, "type": "tag", "name": "unusual pupils", "url": "/tag/unusual-pupils/", "count": 11168}, {"id": 15658, "type": "tag", "name": "bondage", "url": "/tag/bondage/", "count": 43005}, {"id": 33172, "type": "category", "name": "doujinshi", "url": "/category/doujinshi/", "count": 313439}, {"id": 50863, "type": "artist", "name": "poriuretan", "url": "/artist/poriuretan/", "count": 95}], "num_pages": 9, "num_favorites": 0}