{"id": 428973, "media_id": "2382399", "title": {"english": "[\u671d\u6bd4\u5948\u5409\u5229] \u697d\u5712\u306e\u89b3\u6e2c\u8005 (\u30d6\u30eb\u30fc\u30a2\u30fc\u30ab\u30a4\u30d6)", "japanese": "[\u671d\u6bd4\u5948\u5409\u5229] \u697d\u5712\u306e\u89b3\u6e2c\u8005 (\u30d6\u30eb\u30fc\u30a2\u30fc\u30ab\u30a4\u30d6)", "pretty": "\u697d\u5712\u306e\u89b3\u6e2c\u8005"}, "images": {"pages": [{"t": "j", "w": 1200, "h": 630}, {"t": "p", "w": 1000, "h": 1419}, {"t": "j", "w": 1000, "h": 1419}, {"t": "j", "w": 1000, "h": 1419}, {"t": "p", "w": 1000, "h": 1419}, {"t": "j", "w": 1000, "h": 1419}, {"t": "p", "w": 1000, "h": 1419}, {"t": "j", "w": 1000, "h": 1419}, {"t": "j", "w": 1000, "h": 1419}, {"t": "j", "w": 1000, "h": 1419}, {"t": "j", "w": 1000, "h": 1419}, {"t": "j", "w": 1000, "h": 1419}, {"t": "j", "w": 1000, "h": 1419}, {"t": "j", "w": 1000, "h": 1419}, {"t": "j", "w": 1000, "h": 1419}, {"t": "j", "w": 1000, "h": 1419}], "cover": {"t": "j", "w": 350, "h": 184}, "thumbnail": {"t": "j", "w": 250, "h": 131}}, "scanlator": "", "upload_date": 1669094301, "tags": [{"id": 6346, "type": "language", "name": "japanese", "url": "/language/japanese/", "count": 238378}, {"id": 32282, "type": "tag", "name": "piss drinking", "url": "/tag/piss-drinking/", "count": 1892}, {"id": 33172, "type": "category", "name": "doujinshi", "url": "/category/doujinshi/", "count": 313008}, {"id": 128408, "type": "parody", "name": "blue archive", "url": "/parody/blue-archive/", "count": 584}], "num_pages": 16, "num_favorites": 0}