{"id": 421863, "media_id": "2336960", "title": {"english": "[50on! (Aiue Oka)] Saimin Seishidou 4.5 Mikage Yuuki no Baai [Chinese] [DL\u7248]", "japanese": "[50on! (\u611b\u4e0a\u9678)] \u50ac\u7720\u6027\u6307\u5c0e4.5 \u5fa1\u5f71\u53cb\u59eb\u306e\u5834\u5408 [\u4e2d\u56fd\u7ffb\u8a33] [DL\u7248]", "pretty": "Saimin Seishidou 4.5 Mikage Yuuki no Baai"}, "images": {"pages": [{"t": "j", "w": 1058, "h": 1454}, {"t": "j", "w": 1280, "h": 891}, {"t": "j", "w": 1065, "h": 1489}, {"t": "j", "w": 1065, "h": 1489}, {"t": "j", "w": 1065, "h": 1489}, {"t": "j", "w": 1065, "h": 1489}, {"t": "j", "w": 1065, "h": 1489}, {"t": "j", "w": 1065, "h": 1489}, {"t": "j", "w": 1065, "h": 1489}, {"t": "j", "w": 1065, "h": 1489}, {"t": "j", "w": 1065, "h": 1489}, {"t": "j", "w": 1065, "h": 1489}, {"t": "j", "w": 1065, "h": 1489}, {"t": "j", "w": 1065, "h": 1489}, {"t": "j", "w": 1065, "h": 1489}, {"t": "j", "w": 1065, "h": 1489}, {"t": "j", "w": 1065, "h": 1489}, {"t": "j", "w": 1065, "h": 1489}, {"t": "j", "w": 1065, "h": 1489}, {"t": "j", "w": 1065, "h": 1489}, {"t": "j", "w": 1065, "h": 1489}, {"t": "j", "w": 1065, "h": 1489}, {"t": "j", "w": 1065, "h": 1489}, {"t": "j", "w": 1065, "h": 1489}, {"t": "j", "w": 1065, "h": 1489}, {"t": "j", "w": 1065, "h": 1489}, {"t": "j", "w": 1065, "h": 1489}, {"t": "j", "w": 1065, "h": 1489}, {"t": "j", "w": 1065, "h": 1489}, {"t": "j", "w": 1065, "h": 1489}, {"t": "j", "w": 1065, "h": 1489}, {"t": "j", "w": 1065, "h": 1489}, {"t": "j", "w": 1065, "h": 1489}, {"t": "j", "w": 1065, "h": 1489}, {"t": "j", "w": 1065, "h": 1489}, {"t": "j", "w": 1065, "h": 1489}, {"t": "j", "w": 1065, "h": 1489}, {"t": "j", "w": 1065, "h": 1489}, {"t": "j", "w": 1065, "h": 1489}, {"t": "j", "w": 1065, "h": 1489}, {"t": "j", "w": 1065, "h": 1489}, {"t": "j", "w": 1065, "h": 1489}, {"t": "j", "w": 1065, "h": 1489}, {"t": "j", "w": 1065, "h": 1489}, {"t": "j", "w": 1065, "h": 1489}, {"t": "j", "w": 1065, "h": 1489}, {"t": "j", "w": 1065, "h": 1489}, {"t": "j", "w": 1065, "h": 1489}, {"t": "j", "w": 1065, "h": 1489}, {"t": "j", "w": 1065, "h": 1489}, {"t": "j", "w": 1065, "h": 1489}, {"t": "j", "w": 1065, "h": 1489}, {"t": "j", "w": 1065, "h": 1489}, {"t": "j", "w": 1065, "h": 1489}, {"t": "j", "w": 1065, "h": 1489}, {"t": "j", "w": 1031, "h": 1454}], "cover": {"t": "j", "w": 350, "h": 481}, "thumbnail": {"t": "j", "w": 250, "h": 344}}, "scanlator": "", "upload_date": 1664266351, "tags": [{"id": 2937, "type": "tag", "name": "big breasts", "url": "/tag/big-breasts/", "count": 140089}, {"id": 8378, "type": "tag", "name": "glasses", "url": "/tag/glasses/", "count": 60284}, {"id": 13720, "type": "tag", "name": "nakadashi", "url": "/tag/nakadashi/", "count": 63868}, {"id": 16828, "type": "tag", "name": "hairy", "url": "/tag/hairy/", "count": 15978}, {"id": 17249, "type": "language", "name": "translated", "url": "/language/translated/", "count": 168602}, {"id": 17349, "type": "tag", "name": "tracksuit", "url": "/tag/tracksuit/", "count": 2287}, {"id": 19899, "type": "tag", "name": "exhibitionism", "url": "/tag/exhibitionism/", "count": 12499}, {"id": 20035, "type": "tag", "name": "x-ray", "url": "/tag/x-ray/", "count": 28870}, {"id": 20617, "type": "tag", "name": "mind control", "url": "/tag/mind-control/", "count": 14080}, {"id": 26130, "type": "tag", "name": "fingering", "url": "/tag/fingering/", "count": 8475}, {"id": 28550, "type": "tag", "name": "teacher", "url": "/tag/teacher/", "count": 13119}, {"id": 29366, "type": "tag", "name": "tomboy", "url": "/tag/tomboy/", "count": 4021}, {"id": 29963, "type": "language", "name": "chinese", "url": "/language/chinese/", "count": 79352}, {"id": 31880, "type": "tag", "name": "bbm", "url": "/tag/bbm/", "count": 16729}, {"id": 33172, "type": "category", "name": "doujinshi", "url": "/category/doujinshi/", "count": 311669}, {"id": 33902, "type": "artist", "name": "aiue oka", "url": "/artist/aiue-oka/", "count": 136}, {"id": 34592, "type": "group", "name": "50on", "url": "/group/50on/", "count": 86}, {"id": 90671, "type": "parody", "name": "original", "url": "/parody/original/", "count": 54502}], "num_pages": 56, "num_favorites": 5713}