{"id": "432779", "media_id": "2409202", "title": {"english": "(HaruCC23) [Ohirune(Tsou)] Itadakimasu. Meshiagare. (Kaitou Joker)", "japanese": "(HaruCC23) [\u304a\u3072\u308b\u306d(\u30c4\u30a9\u30a6)] \u3044\u305f\u3060\u304d\u307e\u3059\u3002\u3081\u3057\u3042\u304c\u308c\u3002(\u602a\u76d7\u30b8\u30e7\u30fc\u30ab\u30fc)", "pretty": "Itadakimasu. Meshiagare."}, "images": {"pages": [{"t": "j", "w": 1280, "h": 1828}, {"t": "j", "w": 1280, "h": 1877}, {"t": "j", "w": 1280, "h": 1877}, {"t": "j", "w": 1280, "h": 1877}, {"t": "j", "w": 1280, "h": 1877}, {"t": "j", "w": 1280, "h": 1877}, {"t": "j", "w": 1280, "h": 1877}, {"t": "j", "w": 1280, "h": 1877}, {"t": "j", "w": 1280, "h": 1877}, {"t": "j", "w": 1280, "h": 1877}, {"t": "j", "w": 1280, "h": 1877}, {"t": "j", "w": 1280, "h": 1877}, {"t": "j", "w": 1280, "h": 1877}, {"t": "j", "w": 1280, "h": 1877}, {"t": "j", "w": 1280, "h": 1877}, {"t": "j", "w": 1280, "h": 1877}, {"t": "j", "w": 1280, "h": 1877}, {"t": "j", "w": 1280, "h": 1877}, {"t": "j", "w": 1280, "h": 1877}, {"t": "j", "w": 1280, "h": 1877}, {"t": "j", "w": 1280, "h": 1877}, {"t": "j", "w": 1280, "h": 1877}, {"t": "j", "w": 1280, "h": 1866}, {"t": "j", "w": 1280, "h": 1828}], "cover": {"t": "j", "w": 350, "h": 500}, "thumbnail": {"t": "j", "w": 250, "h": 357}}, "scanlator": "", "upload_date": 1671691937, "tags": [{"id": 6346, "type": "language", "name": "japanese", "url": "/language/japanese/", "count": 240159}, {"id": 14283, "type": "tag", "name": "anal", "url": "/tag/anal/", "count": 86583}, {"id": 16107, "type": "parody", "name": "kaitou joker", "url": "/parody/kaitou-joker/", "count": 22}, {"id": 21712, "type": "tag", "name": "males only", "url": "/tag/males-only/", "count": 34354}, {"id": 23895, "type": "tag", "name": "yaoi", "url": "/tag/yaoi/", "count": 41324}, {"id": 29859, "type": "tag", "name": "blowjob", "url": "/tag/blowjob/", "count": 58791}, {"id": 32341, "type": "tag", "name": "shotacon", "url": "/tag/shotacon/", "count": 50479}, {"id": 33172, "type": "category", "name": "doujinshi", "url": "/category/doujinshi/", "count": 316074}, {"id": 130025, "type": "tag", "name": "anal intercourse", "url": "/tag/anal-intercourse/", "count": 6889}], "num_pages": 24, "num_favorites": 0}