{"id": 423971, "media_id": "2350361", "title": {"english": "1764122-[Meme50] Somerare+Asobizakari [Chinese] [\u7121\u90aa\u6c17\u6f22\u5316\u7d44]", "japanese": null, "pretty": "1764122-Somerare+Asobizakari"}, "images": {"pages": [{"t": "j", "w": 1200, "h": 1695}, {"t": "j", "w": 1200, "h": 1695}, {"t": "j", "w": 1200, "h": 1695}, {"t": "j", "w": 1200, "h": 1695}, {"t": "j", "w": 1200, "h": 1695}, {"t": "j", "w": 1200, "h": 1695}, {"t": "j", "w": 1200, "h": 1694}, {"t": "j", "w": 1200, "h": 1695}, {"t": "j", "w": 1200, "h": 1694}, {"t": "j", "w": 1200, "h": 1694}, {"t": "j", "w": 1200, "h": 1694}, {"t": "j", "w": 1200, "h": 1694}, {"t": "j", "w": 1200, "h": 1694}, {"t": "j", "w": 1200, "h": 1695}, {"t": "j", "w": 1200, "h": 1694}, {"t": "j", "w": 1200, "h": 1694}, {"t": "j", "w": 1200, "h": 1695}, {"t": "j", "w": 1200, "h": 1694}, {"t": "j", "w": 1200, "h": 1695}, {"t": "j", "w": 1200, "h": 1695}, {"t": "j", "w": 1200, "h": 1694}, {"t": "j", "w": 1200, "h": 1694}, {"t": "j", "w": 1200, "h": 1694}, {"t": "j", "w": 1200, "h": 1694}, {"t": "j", "w": 1200, "h": 1694}, {"t": "j", "w": 1200, "h": 1694}, {"t": "j", "w": 1200, "h": 1694}, {"t": "j", "w": 1200, "h": 1694}, {"t": "j", "w": 1200, "h": 1694}, {"t": "j", "w": 1200, "h": 1694}, {"t": "j", "w": 1200, "h": 1694}, {"t": "j", "w": 1200, "h": 1694}, {"t": "j", "w": 1200, "h": 1694}, {"t": "j", "w": 1200, "h": 1694}, {"t": "j", "w": 1200, "h": 1694}, {"t": "j", "w": 1200, "h": 1694}, {"t": "j", "w": 1200, "h": 1694}, {"t": "j", "w": 1200, "h": 1694}, {"t": "j", "w": 1280, "h": 720}], "cover": {"t": "j", "w": 350, "h": 494}, "thumbnail": {"t": "j", "w": 250, "h": 353}}, "scanlator": "", "upload_date": 1665696316, "tags": [{"id": 2937, "type": "tag", "name": "big breasts", "url": "/tag/big-breasts/", "count": 138989}, {"id": 7432, "type": "artist", "name": "meme50", "url": "/artist/meme50/", "count": 157}, {"id": 14283, "type": "tag", "name": "anal", "url": "/tag/anal/", "count": 84960}, {"id": 29963, "type": "language", "name": "chinese", "url": "/language/chinese/", "count": 78280}, {"id": 33172, "type": "category", "name": "doujinshi", "url": "/category/doujinshi/", "count": 309175}], "num_pages": 39, "num_favorites": 0}