{"id": 416843, "media_id": "2308082", "title": {"english": "[Giuniu] Ue no Okuchi to Shita no Okuchi to, [Chinese] [\u672a\u6765\u53ef\u5bc4\u4e2a\u4eba\u91cd\u5d4c] [Decensored] [Digital]", "japanese": "[\u304e\u3046\u306b\u3046] \u4e0a\u306e\u304a\u304f\u3061\u3068\u4e0b\u306e\u304a\u304f\u3061\u3068\u3001 [\u4e2d\u56fd\u7ffb\u8a33] [\u7121\u4fee\u6b63] [DL\u7248]", "pretty": "Ue no Okuchi to Shita no Okuchi to,"}, "images": {"pages": [{"t": "j", "w": 1046, "h": 1500}, {"t": "j", "w": 1046, "h": 1500}, {"t": "j", "w": 1046, "h": 1500}, {"t": "j", "w": 1046, "h": 1500}, {"t": "j", "w": 1046, "h": 1500}, {"t": "j", "w": 1046, "h": 1500}, {"t": "j", "w": 1045, "h": 1500}, {"t": "j", "w": 1046, "h": 1500}, {"t": "j", "w": 1045, "h": 1500}, {"t": "j", "w": 1045, "h": 1500}, {"t": "j", "w": 1046, "h": 1500}, {"t": "j", "w": 1046, "h": 1500}, {"t": "j", "w": 1045, "h": 1500}, {"t": "j", "w": 1046, "h": 1500}, {"t": "j", "w": 1045, "h": 1500}, {"t": "j", "w": 1046, "h": 1500}, {"t": "j", "w": 1046, "h": 1500}, {"t": "j", "w": 1046, "h": 1500}, {"t": "j", "w": 1046, "h": 1500}, {"t": "j", "w": 1046, "h": 1500}, {"t": "j", "w": 1046, "h": 1500}, {"t": "j", "w": 1046, "h": 1500}, {"t": "j", "w": 1045, "h": 1500}, {"t": "j", "w": 1046, "h": 1500}, {"t": "j", "w": 1046, "h": 1500}, {"t": "j", "w": 1045, "h": 1500}, {"t": "j", "w": 1046, "h": 1500}, {"t": "j", "w": 1280, "h": 1085}, {"t": "j", "w": 1280, "h": 1085}, {"t": "j", "w": 1280, "h": 1085}, {"t": "j", "w": 1280, "h": 1085}], "cover": {"t": "j", "w": 350, "h": 502}, "thumbnail": {"t": "j", "w": 250, "h": 358}}, "scanlator": "", "upload_date": 1661317113, "tags": [{"id": 6040, "type": "artist", "name": "giuniu", "url": "/artist/giuniu/", "count": 62}, {"id": 8693, "type": "tag", "name": "uncensored", "url": "/tag/uncensored/", "count": 11932}, {"id": 17249, "type": "language", "name": "translated", "url": "/language/translated/", "count": 167844}, {"id": 29963, "type": "language", "name": "chinese", "url": "/language/chinese/", "count": 78835}, {"id": 33172, "type": "category", "name": "doujinshi", "url": "/category/doujinshi/", "count": 310428}, {"id": 35762, "type": "tag", "name": "sole female", "url": "/tag/sole-female/", "count": 107497}, {"id": 35763, "type": "tag", "name": "sole male", "url": "/tag/sole-male/", "count": 95807}], "num_pages": 31, "num_favorites": 2910}